{"nodes": [{"id": "index_page", "label": "index.html \u2014 landing page (bunny intro + scroll home)", "file_type": "code", "source_file": "index.html", "source_location": null, "source_url": null, "captured_at": null, "author": null, "contributor": null}, {"id": "index_gsap_library", "label": "GSAP core library (local, no ScrollTrigger)", "file_type": "concept", "source_file": "index.html", "source_location": null, "source_url": null, "captured_at": null, "author": null, "contributor": null}, {"id": "index_lottie_animation", "label": "Lottie bunny mascot animation (CONEJO data)", "file_type": "concept", "source_file": "index.html", "source_location": null, "source_url": null, "captured_at": null, "author": null, "contributor": null}, {"id": "index_foto_portada", "label": "foto-portada.jpg hero image", "file_type": "concept", "source_file": "index.html", "source_location": null, "source_url": null, "captured_at": null, "author": null, "contributor": null}, {"id": "index_reveal_scroll_animation", "label": "Line-by-line scroll reveal pattern (.line + IntersectionObserver + GSAP)", "file_type": "concept", "source_file": "index.html", "source_location": null, "source_url": null, "captured_at": null, "author": null, "contributor": null}, {"id": "index_main_script", "label": "Top-level init script (hash-based intro dispatch)", "file_type": "code", "source_file": "index.html", "source_location": null, "source_url": null, "captured_at": null, "author": null, "contributor": null}, {"id": "index_iralmenu", "label": "irAlMenu()", "file_type": "code", "source_file": "index.html", "source_location": null, "source_url": null, "captured_at": null, "author": null, "contributor": null}, {"id": "index_animarhome", "label": "animarHome()", "file_type": "code", "source_file": "index.html", "source_location": null, "source_url": null, "captured_at": null, "author": null, "contributor": null}, {"id": "index_lerp", "label": "lerp(a, b, t)", "file_type": "code", "source_file": "index.html", "source_location": null, "source_url": null, "captured_at": null, "author": null, "contributor": null}, {"id": "index_actualizarhero", "label": "actualizarHero()", "file_type": "code", "source_file": "index.html", "source_location": null, "source_url": null, "captured_at": null, "author": null, "contributor": null}, {"id": "index_intro_reveal_effect", "label": "Intro manifiesto reveal IIFE (IntersectionObserver)", "file_type": "code", "source_file": "index.html", "source_location": null, "source_url": null, "captured_at": null, "author": null, "contributor": null}, {"id": "index_actualizarcorto", "label": "actualizarCorto()", "file_type": "code", "source_file": "index.html", "source_location": null, "source_url": null, "captured_at": null, "author": null, "contributor": null}, {"id": "index_alscroll", "label": "alScroll() (rAF-throttled scroll handler for corto section)", "file_type": "code", "source_file": "index.html", "source_location": null, "source_url": null, "captured_at": null, "author": null, "contributor": null}, {"id": "index_abrirvisor", "label": "abrirVisor()", "file_type": "code", "source_file": "index.html", "source_location": null, "source_url": null, "captured_at": null, "author": null, "contributor": null}, {"id": "index_cerrarvisor", "label": "cerrarVisor()", "file_type": "code", "source_file": "index.html", "source_location": null, "source_url": null, "captured_at": null, "author": null, "contributor": null}, {"id": "index_reproducirintro", "label": "reproducirIntro()", "file_type": "code", "source_file": "index.html", "source_location": null, "source_url": null, "captured_at": null, "author": null, "contributor": null}], "edges": [{"source": "index_page", "target": "knox_page", "relation": "references", "confidence": "EXTRACTED", "confidence_score": 1.0, "source_file": "index.html", "source_location": null, "weight": 1.0}, {"source": "index_page", "target": "trabajos_page", "relation": "references", "confidence": "EXTRACTED", "confidence_score": 1.0, "source_file": "index.html", "source_location": null, "weight": 1.0}, {"source": "index_page", "target": "contacto_page", "relation": "references", "confidence": "EXTRACTED", "confidence_score": 1.0, "source_file": "index.html", "source_location": null, "weight": 1.0}, {"source": "index_page", "target": "index_gsap_library", "relation": "references", "confidence": "EXTRACTED", "confidence_score": 1.0, "source_file": "index.html", "source_location": null, "weight": 1.0}, {"source": "index_page", "target": "index_lottie_animation", "relation": "references", "confidence": "EXTRACTED", "confidence_score": 1.0, "source_file": "index.html", "source_location": null, "weight": 1.0}, {"source": "index_page", "target": "index_foto_portada", "relation": "references", "confidence": "EXTRACTED", "confidence_score": 1.0, "source_file": "index.html", "source_location": null, "weight": 1.0}, {"source": "index_reproducirintro", "target": "index_lottie_animation", "relation": "implements", "confidence": "EXTRACTED", "confidence_score": 1.0, "source_file": "index.html", "source_location": null, "weight": 1.0}, {"source": "index_reproducirintro", "target": "index_animarhome", "relation": "calls", "confidence": "EXTRACTED", "confidence_score": 1.0, "source_file": "index.html", "source_location": null, "weight": 1.0}, {"source": "index_reproducirintro", "target": "index_actualizarhero", "relation": "calls", "confidence": "EXTRACTED", "confidence_score": 1.0, "source_file": "index.html", "source_location": null, "weight": 1.0}, {"source": "index_main_script", "target": "index_iralmenu", "relation": "calls", "confidence": "EXTRACTED", "confidence_score": 1.0, "source_file": "index.html", "source_location": null, "weight": 1.0}, {"source": "index_main_script", "target": "index_reproducirintro", "relation": "calls", "confidence": "EXTRACTED", "confidence_score": 1.0, "source_file": "index.html", "source_location": null, "weight": 1.0}, {"source": "index_iralmenu", "target": "index_actualizarhero", "relation": "calls", "confidence": "EXTRACTED", "confidence_score": 1.0, "source_file": "index.html", "source_location": null, "weight": 1.0}, {"source": "index_iralmenu", "target": "index_gsap_library", "relation": "references", "confidence": "EXTRACTED", "confidence_score": 1.0, "source_file": "index.html", "source_location": null, "weight": 1.0}, {"source": "index_alscroll", "target": "index_actualizarcorto", "relation": "calls", "confidence": "EXTRACTED", "confidence_score": 1.0, "source_file": "index.html", "source_location": null, "weight": 1.0}, {"source": "index_actualizarcorto", "target": "docs_superpowers_specs_2026_07_08_seccion_corto_design_parallax_continuo", "relation": "implements", "confidence": "EXTRACTED", "confidence_score": 1.0, "source_file": "index.html", "source_location": null, "weight": 1.0}, {"source": "index_actualizarcorto", "target": "index_actualizarhero", "relation": "conceptually_related_to", "confidence": "EXTRACTED", "confidence_score": 1.0, "source_file": "index.html", "source_location": null, "weight": 1.0}, {"source": "index_actualizarcorto", "target": "index_lerp", "relation": "calls", "confidence": "EXTRACTED", "confidence_score": 1.0, "source_file": "index.html", "source_location": null, "weight": 1.0}, {"source": "index_actualizarhero", "target": "index_lerp", "relation": "calls", "confidence": "EXTRACTED", "confidence_score": 1.0, "source_file": "index.html", "source_location": null, "weight": 1.0}, {"source": "index_abrirvisor", "target": "docs_superpowers_specs_2026_07_08_seccion_corto_design_visor_lightbox", "relation": "implements", "confidence": "EXTRACTED", "confidence_score": 1.0, "source_file": "index.html", "source_location": null, "weight": 1.0}, {"source": "index_cerrarvisor", "target": "docs_superpowers_specs_2026_07_08_seccion_corto_design_visor_lightbox", "relation": "implements", "confidence": "EXTRACTED", "confidence_score": 1.0, "source_file": "index.html", "source_location": null, "weight": 1.0}, {"source": "index_intro_reveal_effect", "target": "index_reveal_scroll_animation", "relation": "implements", "confidence": "EXTRACTED", "confidence_score": 1.0, "source_file": "index.html", "source_location": null, "weight": 1.0}, {"source": "docs_superpowers_specs_2026_07_08_seccion_corto_design_seccion_corto", "target": "index_reveal_scroll_animation", "relation": "references", "confidence": "EXTRACTED", "confidence_score": 1.0, "source_file": "index.html", "source_location": null, "weight": 1.0}], "hyperedges": [{"id": "site_navigation_pages", "label": "Shared site navigation across the four pages", "nodes": ["index_page", "knox_page", "trabajos_page", "contacto_page", "contacto_pagina_css_stylesheet"], "relation": "participate_in", "confidence": "EXTRACTED", "confidence_score": 1.0, "source_file": "index.html"}]}